fargopy/__init__.py
fargopy/fields.py
fargopy/flux.py
fargopy/fsimulation.py
fargopy/plot.py
fargopy/simulation.py
fargopy/sys.py
fargopy/util.py
fargopy/version.py
fargopy/tests/test___init__.py
fargopy-0.4.0.data/scripts/ifargopy
fargopy-0.4.0.dist-info/licenses/LICENSE
fargopy-0.4.0.dist-info/METADATA
fargopy-0.4.0.dist-info/WHEEL
fargopy-0.4.0.dist-info/entry_points.txt
fargopy-0.4.0.dist-info/top_level.txt
fargopy-0.4.0.dist-info/RECORD
