Metadata-Version: 2.4
Name: fargopy
Version: 0.4.0
Summary: FARGO3D Wrapping
Home-page: https://pypi.org/project/fargopy
Author: Jorge Zuluaga, Alejandro Murillo-González, Matias Montesinos
Author-email: jorge.zuluaga@gmail.com
License: MIT
Keywords: astronomy MHD CFD
Classifier: Programming Language :: Python :: 3
Classifier: License :: OSI Approved :: MIT License
Classifier: Operating System :: OS Independent
License-File: LICENSE
Requires-Dist: scipy
Requires-Dist: matplotlib
Requires-Dist: tqdm
Requires-Dist: numpy
Requires-Dist: ipython
Requires-Dist: joblib
Requires-Dist: celluloid
Requires-Dist: psutil
Requires-Dist: gdown
Requires-Dist: pandas
Requires-Dist: plotly
Requires-Dist: ipywidgets
Requires-Dist: nbformat
Dynamic: author
Dynamic: author-email
Dynamic: classifier
Dynamic: description
Dynamic: description-content-type
Dynamic: home-page
Dynamic: keywords
Dynamic: license
Dynamic: license-file
Dynamic: requires-dist
Dynamic: summary
